clear.py
pylion.py
pylion_ce-0.0.1.dist-info/METADATA
pylion_ce-0.0.1.dist-info/WHEEL
pylion_ce-0.0.1.dist-info/top_level.txt
pylion_ce-0.0.1.dist-info/RECORD
