Metadata-Version: 2.1
Name: pylion-ce
Version: 0.0.1
Summary: pylion is a tor v3 link generator
Author: Invizabel
Project-URL: Homepage, https://github.com/Invizabel/pylion
Project-URL: Bug Tracker, https://github.com/Invizabel/pylion/issues
Classifier: Programming Language :: Python :: 3
Classifier: License :: OSI Approved :: MIT License
Classifier: Operating System :: OS Independent
Requires-Python: >=3.7
Requires-Dist: cryptography
